MANIFEST.in
README.rst
jupyter_sigplot.json
requirements-dev.txt
requirements.txt
setup.cfg
setup.py
jupyter_sigplot/__init__.py
jupyter_sigplot/_version.py
jupyter_sigplot/sigplot.py
jupyter_sigplot.egg-info/PKG-INFO
jupyter_sigplot.egg-info/SOURCES.txt
jupyter_sigplot.egg-info/dependency_links.txt
jupyter_sigplot.egg-info/not-zip-safe
jupyter_sigplot.egg-info/top_level.txt
jupyter_sigplot/static/extension.js
jupyter_sigplot/static/index.js
jupyter_sigplot/static/index.js.map
test/__init__.py
test/test_extension.py
test/test_jupyter_sigplot.py
test/testutil.py