Metadata-Version: 1.1
Name: jupyter-sigplot
Version: 0.2.0
Summary: Jupyter Notebook Widget for the SigPlot plotting library
Home-page: https://github.com/LGSInnovations/jupyter-sigplot
Author: LGS Innovations
Author-email: sigplot@lgsinnovations.com
License: UNKNOWN
Keywords: ipython,jupyter,widgets,sigplot,plot,plotting,dsp,sdr,software defined radio
Platform: UNKNOWN
Classifier: Development Status :: 4 - Beta
Classifier: Framework :: IPython
Classifier: Intended Audience :: Developers
Classifier: Intended Audience :: Science/Research
Classifier: Topic :: Multimedia :: Graphics
Classifier: Programming Language :: Python :: 2
Classifier: Programming Language :: Python :: 2.7
Classifier: Programming Language :: Python :: 3
Classifier: Programming Language :: Python :: 3.3
Classifier: Programming Language :: Python :: 3.4
Classifier: Programming Language :: Python :: 3.5
